carrot/__init__.py
carrot/carrot.py
carrot/src.py
carrot_rpc-0.3.1.dist-info/LICENSE
carrot_rpc-0.3.1.dist-info/METADATA
carrot_rpc-0.3.1.dist-info/WHEEL
carrot_rpc-0.3.1.dist-info/top_level.txt
carrot_rpc-0.3.1.dist-info/RECORD
