Metadata-Version: 2.1
Name: carrot-rpc
Version: 0.3.1
Summary: CarrotRPC it is a python asyncio RPC server/client for RabbitMQ with pydantic schema that allows you to make RPC calls.
Home-page: https://github.com/Sobolev5/carrot-rpc
Author: Sobolev Andrey
Author-email: email.asobolev@gmail.com
License: UNKNOWN
Platform: UNKNOWN
Classifier: Programming Language :: Python :: 3
Classifier: License :: OSI Approved :: MIT License
Classifier: Operating System :: OS Independent
Requires-Python: >=3.9
License-File: LICENSE
Requires-Dist: aiormq (>=6.4.2)
Requires-Dist: orjson (>=3.8.0)
Requires-Dist: pydantic (>=2.0.0)
